{
  "hardware": "Intel i9-9900K @ 3.6GHz, TDP=95.0W, 8 logical cores",
  "T_op_K": 330.0,
  "K_B": 1.380649e-23,
  "run_ticks": 2000000,
  "n_trials": 5,
  "phases": {
    "idle_pre": {
      "label": "idle_pre",
      "n": 397,
      "duration_s": 19.998,
      "mean_qemu_cpu_pct": 0.0,
      "total_Q_proc_J": 0.0,
      "delta_S_proc_JK": 0.0,
      "delta_S_proc_kB": 0.0,
      "mean_sys_util": 0.06479,
      "total_Q_sys_J": 122.1702,
      "delta_S_sys_JK": 0.3702127,
      "est_instructions": 0,
      "landauer_dS_JK": 0.0,
      "landauer_dS_kB": 0.0
    },
    "boot_only": {
      "label": "boot_only",
      "n": 4,
      "duration_s": 0.152,
      "mean_qemu_cpu_pct": 54.48,
      "total_Q_proc_J": 1.29378,
      "delta_S_proc_JK": 0.00392055,
      "delta_S_proc_kB": 2.8396422569561434e+20,
      "mean_sys_util": 0.15418,
      "total_Q_sys_J": 2.9295,
      "delta_S_sys_JK": 0.0088772,
      "est_instructions": 297966847,
      "landauer_dS_JK": 0.0,
      "landauer_dS_kB": 206534826.1,
      "qemu_rc": 33,
      "qemu_dur": 0.181
    },
    "o1_bootstrap": [
      {
        "label": "O1_BOOTSTRAP_1",
        "n": 42,
        "duration_s": 2.062,
        "mean_qemu_cpu_pct": 106.08,
        "total_Q_proc_J": 26.45275,
        "delta_S_proc_JK": 0.08015985,
        "delta_S_proc_kB": 5.80595419145985e+21,
        "mean_sys_util": 0.23323,
        "total_Q_sys_J": 46.5294,
        "delta_S_sys_JK": 0.1409983,
        "est_instructions": 7872691862,
        "landauer_dS_JK": 0.0,
        "landauer_dS_kB": 5456932746.07,
        "qemu_rc": 33,
        "qemu_dur": 2.09,
        "output_tick": "Tick:  2000000  Tier: O_1",
        "frob_line": "Tick:  2000000  Tier: O_1",
        "comp_excess_proc_JK": 0.02697449,
        "comp_excess_proc_kB": 1.953754652989092e+21
      },
      {
        "label": "O1_BOOTSTRAP_2",
        "n": 40,
        "duration_s": 1.961,
        "mean_qemu_cpu_pct": 102.91,
        "total_Q_proc_J": 24.43994,
        "delta_S_proc_JK": 0.07406042,
        "delta_S_proc_kB": 5.364174143222982e+21,
        "mean_sys_util": 0.16439,
        "total_Q_sys_J": 31.2335,
        "delta_S_sys_JK": 0.0946469,
        "est_instructions": 7265873720,
        "landauer_dS_JK": 0.0,
        "landauer_dS_kB": 5036318571.4,
        "qemu_rc": 33,
        "qemu_dur": 1.999,
        "output_tick": "Tick:  2000000  Tier: O_1",
        "frob_line": "Tick:  2000000  Tier: O_1",
        "comp_excess_proc_JK": 0.02348017,
        "comp_excess_proc_kB": 1.7006615281348803e+21
      },
      {
        "label": "O1_BOOTSTRAP_3",
        "n": 41,
        "duration_s": 2.012,
        "mean_qemu_cpu_pct": 102.78,
        "total_Q_proc_J": 25.02122,
        "delta_S_proc_JK": 0.07582188,
        "delta_S_proc_kB": 5.491756050958644e+21,
        "mean_sys_util": 0.15135,
        "total_Q_sys_J": 29.4757,
        "delta_S_sys_JK": 0.0893204,
        "est_instructions": 7445602866,
        "landauer_dS_JK": 0.0,
        "landauer_dS_kB": 5160897289.76,
        "qemu_rc": 33,
        "qemu_dur": 2.011,
        "output_tick": "Tick:  2000000  Tier: O_1",
        "frob_line": "Tick:  2000000  Tier: O_1",
        "comp_excess_proc_JK": 0.02392618,
        "comp_excess_proc_kB": 1.7329660677123956e+21
      },
      {
        "label": "O1_BOOTSTRAP_4",
        "n": 42,
        "duration_s": 2.062,
        "mean_qemu_cpu_pct": 99.88,
        "total_Q_proc_J": 24.90662,
        "delta_S_proc_JK": 0.07547462,
        "delta_S_proc_kB": 5.466604561486748e+21,
        "mean_sys_util": 0.16058,
        "total_Q_sys_J": 32.0362,
        "delta_S_sys_JK": 0.0970794,
        "est_instructions": 7415424505,
        "landauer_dS_JK": 0.0,
        "landauer_dS_kB": 5139979249.37,
        "qemu_rc": 33,
        "qemu_dur": 2.088,
        "output_tick": "Tick:  2000000  Tier: O_1",
        "frob_line": "Tick:  2000000  Tier: O_1",
        "comp_excess_proc_JK": 0.02228926,
        "comp_excess_proc_kB": 1.614404825480435e+21
      },
      {
        "label": "O1_BOOTSTRAP_5",
        "n": 43,
        "duration_s": 2.113,
        "mean_qemu_cpu_pct": 98.47,
        "total_Q_proc_J": 25.14175,
        "delta_S_proc_JK": 0.07618712,
        "delta_S_proc_kB": 5.518210726413536e+21,
        "mean_sys_util": 0.15358,
        "total_Q_sys_J": 31.369,
        "delta_S_sys_JK": 0.0950576,
        "est_instructions": 7490194153,
        "landauer_dS_JK": 0.0,
        "landauer_dS_kB": 5191805606.57,
        "qemu_rc": 33,
        "qemu_dur": 2.134,
        "output_tick": "Tick:  2000000  Tier: O_1",
        "frob_line": "Tick:  2000000  Tier: O_1",
        "comp_excess_proc_JK": 0.02168632,
        "comp_excess_proc_kB": 1.5707335015328978e+21
      }
    ],
    "o1_compound": [
      {
        "label": "O1_COMPOUND_1",
        "n": 58,
        "duration_s": 2.868,
        "mean_qemu_cpu_pct": 101.78,
        "total_Q_proc_J": 35.05025,
        "delta_S_proc_JK": 0.10621288,
        "delta_S_proc_kB": 7.692967494843277e+21,
        "mean_sys_util": 0.21357,
        "total_Q_sys_J": 58.8384,
        "delta_S_sys_JK": 0.1782981,
        "est_instructions": 10507537148,
        "landauer_dS_JK": 0.0,
        "landauer_dS_kB": 7283267851.52,
        "qemu_rc": 33,
        "qemu_dur": 2.904,
        "output_tick": "Tick:  2000000  Tier: O_1",
        "frob_line": "Tick:  2000000  Tier: O_1",
        "comp_excess_proc_JK": 0.03223829,
        "comp_excess_proc_kB": 2.335009972998587e+21
      },
      {
        "label": "O1_COMPOUND_2",
        "n": 55,
        "duration_s": 2.716,
        "mean_qemu_cpu_pct": 102.65,
        "total_Q_proc_J": 33.52075,
        "delta_S_proc_JK": 0.10157803,
        "delta_S_proc_kB": 7.357266785622579e+21,
        "mean_sys_util": 0.16417,
        "total_Q_sys_J": 42.89,
        "delta_S_sys_JK": 0.1299697,
        "est_instructions": 10038216431,
        "landauer_dS_JK": 0.0,
        "landauer_dS_kB": 6957959604.5,
        "qemu_rc": 33,
        "qemu_dur": 2.761,
        "output_tick": "Tick:  2000000  Tier: O_1",
        "frob_line": "Tick:  2000000  Tier: O_1",
        "comp_excess_proc_JK": 0.03152399,
        "comp_excess_proc_kB": 2.2832734346025128e+21
      },
      {
        "label": "O1_COMPOUND_3",
        "n": 59,
        "duration_s": 2.918,
        "mean_qemu_cpu_pct": 103.09,
        "total_Q_proc_J": 36.11544,
        "delta_S_proc_JK": 0.10944072,
        "delta_S_proc_kB": 7.926759060193405e+21,
        "mean_sys_util": 0.15723,
        "total_Q_sys_J": 44.0646,
        "delta_S_sys_JK": 0.1335291,
        "est_instructions": 10829303535,
        "landauer_dS_JK": 0.0,
        "landauer_dS_kB": 7506299257.37,
        "qemu_rc": 33,
        "qemu_dur": 2.918,
        "output_tick": "Tick:  2000000  Tier: O_1",
        "frob_line": "Tick:  2000000  Tier: O_1",
        "comp_excess_proc_JK": 0.03417648,
        "comp_excess_proc_kB": 2.475392169685568e+21
      },
      {
        "label": "O1_COMPOUND_4",
        "n": 55,
        "duration_s": 2.715,
        "mean_qemu_cpu_pct": 107.04,
        "total_Q_proc_J": 34.95406,
        "delta_S_proc_JK": 0.1059214,
        "delta_S_proc_kB": 7.671855881918685e+21,
        "mean_sys_util": 0.16819,
        "total_Q_sys_J": 43.9399,
        "delta_S_sys_JK": 0.1331512,
        "est_instructions": 10462367549,
        "landauer_dS_JK": 0.0,
        "landauer_dS_kB": 7251958679.49,
        "qemu_rc": 33,
        "qemu_dur": 2.763,
        "output_tick": "Tick:  2000000  Tier: O_1",
        "frob_line": "Tick:  2000000  Tier: O_1",
        "comp_excess_proc_JK": 0.03589315,
        "comp_excess_proc_kB": 2.599730629161396e+21
      },
      {
        "label": "O1_COMPOUND_5",
        "n": 56,
        "duration_s": 2.765,
        "mean_qemu_cpu_pct": 107.62,
        "total_Q_proc_J": 35.78353,
        "delta_S_proc_JK": 0.10843494,
        "delta_S_proc_kB": 7.853910963743729e+21,
        "mean_sys_util": 0.18771,
        "total_Q_sys_J": 49.9309,
        "delta_S_sys_JK": 0.1513057,
        "est_instructions": 10713756639,
        "landauer_dS_JK": 0.0,
        "landauer_dS_kB": 7426208273.05,
        "qemu_rc": 33,
        "qemu_dur": 2.777,
        "output_tick": "Tick:  2000000  Tier: O_1",
        "frob_line": "Tick:  2000000  Tier: O_1",
        "comp_excess_proc_JK": 0.03711704,
        "comp_excess_proc_kB": 2.6883762874523037e+21
      }
    ],
    "oinf_chain": [
      {
        "label": "OINF_CHAIN_1",
        "n": 56,
        "duration_s": 2.765,
        "mean_qemu_cpu_pct": 107.28,
        "total_Q_proc_J": 35.66894,
        "delta_S_proc_JK": 0.10808769,
        "delta_S_proc_kB": 7.828759474271838e+21,
        "mean_sys_util": 0.1467,
        "total_Q_sys_J": 39.0224,
        "delta_S_sys_JK": 0.1182496,
        "est_instructions": 10678544092,
        "landauer_dS_JK": 0.0,
        "landauer_dS_kB": 7401800801.74,
        "qemu_rc": 33,
        "qemu_dur": 2.775,
        "output_tick": "Tick:   500000  Tier: O_1",
        "frob_line": "Tick:   500000  Tier: O_1",
        "comp_excess_proc_JK": 0.03676979,
        "comp_excess_proc_kB": 2.6632250723353556e+21
      },
      {
        "label": "OINF_CHAIN_2",
        "n": 57,
        "duration_s": 2.817,
        "mean_qemu_cpu_pct": 107.42,
        "total_Q_proc_J": 36.35531,
        "delta_S_proc_JK": 0.11016761,
        "delta_S_proc_kB": 7.97940777390659e+21,
        "mean_sys_util": 0.13855,
        "total_Q_sys_J": 37.512,
        "delta_S_sys_JK": 0.1136728,
        "est_instructions": 10893438181,
        "landauer_dS_JK": 0.0,
        "landauer_dS_kB": 7550753994.85,
        "qemu_rc": 33,
        "qemu_dur": 2.826,
        "output_tick": "Tick:   500000  Tier: O_1",
        "frob_line": "Tick:   500000  Tier: O_1",
        "comp_excess_proc_JK": 0.03750847,
        "comp_excess_proc_kB": 2.716727389761893e+21
      },
      {
        "label": "OINF_CHAIN_3",
        "n": 58,
        "duration_s": 2.867,
        "mean_qemu_cpu_pct": 101.81,
        "total_Q_proc_J": 35.06153,
        "delta_S_proc_JK": 0.10624706,
        "delta_S_proc_kB": 7.695443548210975e+21,
        "mean_sys_util": 0.14287,
        "total_Q_sys_J": 39.3612,
        "delta_S_sys_JK": 0.1192765,
        "est_instructions": 10508158403,
        "landauer_dS_JK": 0.0,
        "landauer_dS_kB": 7283698472.56,
        "qemu_rc": 33,
        "qemu_dur": 2.901,
        "output_tick": "Tick:   500000  Tier: O_1",
        "frob_line": "Tick:   500000  Tier: O_1",
        "comp_excess_proc_JK": 0.03229826,
        "comp_excess_proc_kB": 2.3393538063773283e+21
      },
      {
        "label": "OINF_CHAIN_4",
        "n": 59,
        "duration_s": 2.917,
        "mean_qemu_cpu_pct": 100.43,
        "total_Q_proc_J": 35.18325,
        "delta_S_proc_JK": 0.10661591,
        "delta_S_proc_kB": 7.722158860862466e+21,
        "mean_sys_util": 0.14989,
        "total_Q_sys_J": 42.0075,
        "delta_S_sys_JK": 0.1272953,
        "est_instructions": 10546566953,
        "landauer_dS_JK": 0.0,
        "landauer_dS_kB": 7310321243.77,
        "qemu_rc": 33,
        "qemu_dur": 2.916,
        "output_tick": "Tick:   500000  Tier: O_1",
        "frob_line": "Tick:   500000  Tier: O_1",
        "comp_excess_proc_JK": 0.03137746,
        "comp_excess_proc_kB": 2.2726602003077802e+21
      },
      {
        "label": "OINF_CHAIN_5",
        "n": 57,
        "duration_s": 2.817,
        "mean_qemu_cpu_pct": 102.21,
        "total_Q_proc_J": 34.59306,
        "delta_S_proc_JK": 0.10482746,
        "delta_S_proc_kB": 7.592622174152306e+21,
        "mean_sys_util": 0.15509,
        "total_Q_sys_J": 41.9915,
        "delta_S_sys_JK": 0.1272469,
        "est_instructions": 10364737946,
        "landauer_dS_JK": 0.0,
        "landauer_dS_kB": 7184287013.06,
        "qemu_rc": 33,
        "qemu_dur": 2.857,
        "output_tick": "Tick:   500000  Tier: O_1",
        "frob_line": "Tick:   500000  Tier: O_1",
        "comp_excess_proc_JK": 0.03216832,
        "comp_excess_proc_kB": 2.329941899749587e+21
      }
    ],
    "idle_post": {
      "label": "idle_post",
      "n": 298,
      "duration_s": 14.994,
      "mean_qemu_cpu_pct": 0.0,
      "total_Q_proc_J": 0.0,
      "delta_S_proc_JK": 0.0,
      "delta_S_proc_kB": 0.0,
      "mean_sys_util": 0.04668,
      "total_Q_sys_J": 66.0799,
      "delta_S_sys_JK": 0.2002421,
      "est_instructions": 0,
      "landauer_dS_JK": 0.0,
      "landauer_dS_kB": 0.0
    }
  },
  "analysis": {
    "method": "per-process CPU% \u00d7 CORE_W (background-isolated)",
    "CORE_W": 11.875,
    "boot_dS_proc_JK": 0.00392055,
    "boot_rate_JK_s": 0.02579309,
    "o1_bootstrap": {
      "mean_dS_JK": 0.07634078,
      "rate_JK_s": 0.03697964,
      "mean_dur_s": 2.064,
      "mean_qcpu": 102.02
    },
    "o1_compound": {
      "mean_dS_JK": 0.10631759,
      "rate_JK_s": 0.03763988,
      "mean_dur_s": 2.825,
      "mean_qcpu": 104.44,
      "b_live_present": true
    },
    "oinf_chain": {
      "mean_dS_JK": 0.10718915,
      "rate_JK_s": 0.03754436,
      "mean_dur_s": 2.855,
      "mean_qcpu": 103.83,
      "note": "Verticullum 500k + XIV_Tier_Climber 1.5M"
    },
    "rate_ratio_oinf_vs_o1_bootstrap": 1.015271,
    "rate_ratio_o1c_vs_o1b": 1.017854,
    "rate_ratio_oinf_vs_o1c": 0.997462,
    "recovery_sys_util_ratio": 0.7205
  }
}